LICENSE
MANIFEST.in
README.md
README.rst
setup.cfg
setup.py
django_files_library/__init__.py
django_files_library/admin.py
django_files_library/app_settings.py
django_files_library/apps.py
django_files_library/forms.py
django_files_library/models.py
django_files_library/tools.py
django_files_library/urls.py
django_files_library/views.py
django_files_library.egg-info/PKG-INFO
django_files_library.egg-info/SOURCES.txt
django_files_library.egg-info/dependency_links.txt
django_files_library.egg-info/top_level.txt
django_files_library/__pycache__/__init__.cpython-36.pyc
django_files_library/__pycache__/admin.cpython-36.pyc
django_files_library/__pycache__/app_settings.cpython-36.pyc
django_files_library/__pycache__/apps.cpython-36.pyc
django_files_library/__pycache__/forms.cpython-36.pyc
django_files_library/__pycache__/models.cpython-36.pyc
django_files_library/__pycache__/tools.cpython-36.pyc
django_files_library/__pycache__/urls.cpython-36.pyc
django_files_library/__pycache__/views.cpython-36.pyc
django_files_library/migrations/0001_initial.py
django_files_library/migrations/__init__.py
django_files_library/migrations/__pycache__/0001_initial.cpython-36.pyc
django_files_library/migrations/__pycache__/__init__.cpython-36.pyc
django_files_library/static/django_library/css/common.scss
django_files_library/static/django_library/js/scripts.js
django_files_library/templates/django_files_library/add_file.html
django_files_library/templates/django_files_library/django_library_base.html
django_files_library/templates/django_files_library/django_library_empty.html
django_files_library/templates/django_files_library/full_library.html
django_files_library/templates/django_files_library/library_form.html
django_files_library/templates/django_files_library/library_listing.html
django_files_library/templatetags/__init__.py
django_files_library/templatetags/django_files_library.py
django_files_library/templatetags/__pycache__/__init__.cpython-36.pyc
django_files_library/templatetags/__pycache__/django_files_library.cpython-36.pyc
django_files_library/tests/__init__.py
django_files_library/tests/base_setup.py
django_files_library/tests/test_forms.py
